etformat/__init__.py
etformat/_version.py
etformat/calibration.py
etformat/channels.py
etformat/clean.py
etformat/describe.py
etformat/edfdata.py
etformat/edfdata_containers.py
etformat/edffile.py
etformat/edfinfo.py
etformat/export.py
etformat/plot_gaze.py
etformat/plot_saccades.py
etformat/report.py
etformat/saccade_analysis.py
etformat-1.2.0.dist-info/LICENSE
etformat-1.2.0.dist-info/METADATA
etformat-1.2.0.dist-info/WHEEL
etformat-1.2.0.dist-info/top_level.txt
etformat-1.2.0.dist-info/RECORD
