Metadata-Version: 2.1
Name: etformat
Version: 1.2.0
Summary: A Python package for eye-tracking data processing
Home-page: https://github.com/yourusername/etformat
Author: Mohammad Ahsan Khodami
Author-email: ahsan.khodami@gmail.com
Classifier: Programming Language :: Python :: 3
Classifier: License :: OSI Approved :: MIT License
Classifier: Operating System :: OS Independent
Requires-Python: >=3.6
License-File: LICENSE
Requires-Dist: numpy
Requires-Dist: pandas
Requires-Dist: matplotlib
